fastbi.py
fastbi-0.1.2.dist-info/licenses/LICENSE
fastbi-0.1.2.dist-info/METADATA
fastbi-0.1.2.dist-info/WHEEL
fastbi-0.1.2.dist-info/entry_points.txt
fastbi-0.1.2.dist-info/top_level.txt
fastbi-0.1.2.dist-info/RECORD
