Metadata-Version: 2.4
Name: fastbi
Version: 0.1.2
Summary: Scaffold Power BI projects instantly from templates
Author-email: Alejandro Gonzalez Colin <alejandro.gonzalezcolin@outlook.com>
License: MIT
Project-URL: Homepage, https://github.com/AlexCoderlin/fastbi
Project-URL: Repository, https://github.com/AlexCoderlin/fastbi
Project-URL: Issues, https://github.com/AlexCoderlin/fastbi/issues
Keywords: powerbi,power-bi,scaffold,template,cli,pbip
Classifier: Development Status :: 4 - Beta
Classifier: Intended Audience :: Developers
Classifier: Topic :: Software Development :: Build Tools
Classifier: License :: OSI Approved :: MIT License
Classifier: Programming Language :: Python :: 3.10
Classifier: Programming Language :: Python :: 3.11
Classifier: Programming Language :: Python :: 3.12
Classifier: Programming Language :: Python :: 3.13
Requires-Python: >=3.10
License-File: LICENSE
Requires-Dist: typer>=0.16.0
Requires-Dist: rich>=13.0.0
Dynamic: license-file
